{
  "nm": "Icon 04",
  "ddd": 0,
  "h": 200,
  "w": 200,
  "meta": {"g": "@lottiefiles/toolkit-js 0.26.1"},
  "layers": [
    {
      "ty": 4,
      "nm": "icon 6",
      "sr": 1,
      "st": 0,
      "op": 100,
      "ip": 0,
      "hd": false,
      "ddd": 0,
      "bm": 0,
      "hasMask": false,
      "ao": 0,
      "ks": {
        "a": {"a": 0, "k": [994, 438, 0], "ix": 1},
        "s": {"a": 0, "k": [400, 400, 100], "ix": 6},
        "sk": {"a": 0, "k": 0},
        "p": {"a": 0, "k": [100, 100, 0], "ix": 2},
        "r": {"a": 0, "k": 0, "ix": 10},
        "sa": {"a": 0, "k": 0},
        "o": {"a": 0, "k": 100, "ix": 11}
      },
      "ef": [],
      "shapes": [
        {
          "ty": "gr",
          "bm": 0,
          "hd": false,
          "mn": "ADBE Vector Group",
          "nm": "Group 1",
          "ix": 1,
          "cix": 2,
          "np": 2,
          "it": [
            {
              "ty": "sh",
              "bm": 0,
              "hd": false,
              "mn": "ADBE Vector Shape - Group",
              "nm": "Path 1",
              "ix": 1,
              "d": 1,
              "ks": {
                "a": 0,
                "k": {
                  "c": false,
                  "i": [
                    [0, 0],
                    [1.223, -1.958],
                    [9.112, 5.944],
                    [-2.064, 3.303],
                    [-9.112, -5.944],
                    [-1.979, -1.867]
                  ],
                  "o": [
                    [3.33, 3.708],
                    [-2.064, 3.303],
                    [-9.112, -5.944],
                    [2.064, -3.303],
                    [2.675, 1.745],
                    [0, 0]
                  ],
                  "v": [
                    [12.882, 1.664],
                    [16.498, 10.762],
                    [-3.737, 5.981],
                    [-16.498, -10.762],
                    [3.737, -5.981],
                    [10.773, -0.49]
                  ]
                },
                "ix": 2
              }
            },
            {
              "ty": "st",
              "bm": 0,
              "hd": false,
              "mn": "ADBE Vector Graphic - Stroke",
              "nm": "Stroke 1",
              "lc": 2,
              "lj": 2,
              "ml": 1,
              "o": {"a": 0, "k": 100, "ix": 4},
              "w": {"a": 0, "k": 1.5, "ix": 5},
              "c": {"a": 0, "k": [0.702, 0.2431, 0.9843], "ix": 3}
            },
            {
              "ty": "tr",
              "a": {"a": 0, "k": [0, 0], "ix": 1},
              "s": {"a": 0, "k": [100, 100], "ix": 3},
              "sk": {"a": 0, "k": 0, "ix": 4},
              "p": {"a": 0, "k": [994, 438.147], "ix": 2},
              "r": {"a": 0, "k": 0, "ix": 6},
              "sa": {"a": 0, "k": 0, "ix": 5},
              "o": {"a": 0, "k": 100, "ix": 7}
            }
          ]
        },
        {
          "ty": "gr",
          "bm": 0,
          "hd": false,
          "mn": "ADBE Vector Group",
          "nm": "Group 2",
          "ix": 2,
          "cix": 2,
          "np": 2,
          "it": [
            {
              "ty": "sh",
              "bm": 0,
              "hd": false,
              "mn": "ADBE Vector Shape - Group",
              "nm": "Path 1",
              "ix": 1,
              "d": 1,
              "ks": {
                "a": 0,
                "k": {
                  "c": false,
                  "i": [
                    [0, 0],
                    [1.738, 2.332],
                    [-9.097, 7.08],
                    [-2.313, -3.103],
                    [9.097, -7.08],
                    [1.231, -0.817]
                  ],
                  "o": [
                    [-6.564, 3.765],
                    [-2.313, -3.103],
                    [9.097, -7.08],
                    [2.313, 3.103],
                    [-1.243, 0.968],
                    [0, 0]
                  ],
                  "v": [
                    [-2.514, 10.145],
                    [-16.472, 12.819],
                    [-4.189, -5.619],
                    [16.472, -12.819],
                    [4.189, 5.619],
                    [0.469, 8.299]
                  ]
                },
                "ix": 2
              }
            },
            {
              "ty": "st",
              "bm": 0,
              "hd": false,
              "mn": "ADBE Vector Graphic - Stroke",
              "nm": "Stroke 1",
              "lc": 2,
              "lj": 2,
              "ml": 1,
              "o": {"a": 0, "k": 100, "ix": 4},
              "w": {"a": 0, "k": 1.5, "ix": 5},
              "c": {"a": 0, "k": [0.702, 0.2431, 0.9843], "ix": 3}
            },
            {
              "ty": "tr",
              "a": {"a": 0, "k": [0, 0], "ix": 1},
              "s": {"a": 0, "k": [100, 100], "ix": 3},
              "sk": {"a": 0, "k": 0, "ix": 4},
              "p": {"a": 0, "k": [994, 438.092], "ix": 2},
              "r": {"a": 0, "k": 0, "ix": 6},
              "sa": {"a": 0, "k": 0, "ix": 5},
              "o": {"a": 0, "k": 100, "ix": 7}
            }
          ]
        },
        {
          "ty": "gr",
          "bm": 0,
          "hd": false,
          "mn": "ADBE Vector Group",
          "nm": "Group 3",
          "ix": 3,
          "cix": 2,
          "np": 2,
          "it": [
            {
              "ty": "sh",
              "bm": 0,
              "hd": false,
              "mn": "ADBE Vector Shape - Group",
              "nm": "Path 1",
              "ix": 1,
              "d": 1,
              "ks": {
                "a": 0,
                "k": {
                  "c": false,
                  "i": [
                    [0, 0],
                    [-2.033, 0],
                    [0, -10.493],
                    [3.829, 0],
                    [0, 10.493],
                    [-0.755, 3.042]
                  ],
                  "o": [
                    [1.268, -3.819],
                    [3.829, 0],
                    [0, 10.493],
                    [-3.829, 0],
                    [0, -3.956],
                    [0, 0]
                  ],
                  "v": [
                    [-5.129, -12.783],
                    [0, -19],
                    [6.933, 0],
                    [0, 19],
                    [-6.933, 0],
                    [-5.737, -10.67]
                  ]
                },
                "ix": 2
              }
            },
            {
              "ty": "st",
              "bm": 0,
              "hd": false,
              "mn": "ADBE Vector Graphic - Stroke",
              "nm": "Stroke 1",
              "lc": 2,
              "lj": 2,
              "ml": 1,
              "o": {"a": 0, "k": 100, "ix": 4},
              "w": {"a": 0, "k": 1.5, "ix": 5},
              "c": {"a": 0, "k": [0.702, 0.2431, 0.9843], "ix": 3}
            },
            {
              "ty": "tr",
              "a": {"a": 0, "k": [0, 0], "ix": 1},
              "s": {"a": 0, "k": [100, 100], "ix": 3},
              "sk": {"a": 0, "k": 0, "ix": 4},
              "p": {"a": 0, "k": [993.999, 438], "ix": 2},
              "r": {"a": 0, "k": 0, "ix": 6},
              "sa": {"a": 0, "k": 0, "ix": 5},
              "o": {"a": 0, "k": 100, "ix": 7}
            }
          ]
        },
        {
          "ty": "gr",
          "bm": 0,
          "hd": false,
          "mn": "ADBE Vector Group",
          "nm": "Group 4",
          "ix": 4,
          "cix": 2,
          "np": 2,
          "it": [
            {
              "ty": "sh",
              "bm": 0,
              "hd": false,
              "mn": "ADBE Vector Shape - Group",
              "nm": "Path 1",
              "ix": 1,
              "d": 1,
              "ks": {
                "a": 0,
                "k": {
                  "c": true,
                  "i": [
                    [0, -1.105],
                    [1.105, 0],
                    [0, 1.105],
                    [-1.105, 0]
                  ],
                  "o": [
                    [0, 1.105],
                    [-1.105, 0],
                    [0, -1.105],
                    [1.105, 0]
                  ],
                  "v": [
                    [2, 0],
                    [0, 2],
                    [-2, 0],
                    [0, -2]
                  ]
                },
                "ix": 2
              }
            },
            {
              "ty": "st",
              "bm": 0,
              "hd": false,
              "mn": "ADBE Vector Graphic - Stroke",
              "nm": "Stroke 1",
              "lc": 2,
              "lj": 2,
              "ml": 1,
              "o": {"a": 0, "k": 100, "ix": 4},
              "w": {"a": 0, "k": 1.5, "ix": 5},
              "c": {"a": 0, "k": [0.0314, 0.9647, 0.5216], "ix": 3}
            },
            {
              "ty": "tr",
              "a": {"a": 0, "k": [0, 0], "ix": 1},
              "s": {"a": 0, "k": [100, 100], "ix": 3},
              "sk": {"a": 0, "k": 0, "ix": 4},
              "p": {"a": 0, "k": [993.999, 438], "ix": 2},
              "r": {"a": 0, "k": 0, "ix": 6},
              "sa": {"a": 0, "k": 0, "ix": 5},
              "o": {"a": 0, "k": 100, "ix": 7}
            }
          ]
        },
        {
          "ty": "tm",
          "bm": 0,
          "hd": false,
          "mn": "ADBE Vector Filter - Trim",
          "nm": "Trim Paths 1",
          "ix": 5,
          "e": {
            "a": 1,
            "k": [
              {
                "o": {"x": 0.445, "y": 0},
                "i": {"x": 0.151, "y": 1},
                "s": [0],
                "t": 0
              },
              {
                "o": {"x": 0.167, "y": 0},
                "i": {"x": 0.833, "y": 1},
                "s": [100],
                "t": 20
              },
              {
                "o": {"x": 1, "y": 0},
                "i": {"x": 0.555, "y": 1},
                "s": [100],
                "t": 79
              },
              {"s": [0], "t": 99}
            ],
            "ix": 2
          },
          "o": {
            "a": 1,
            "k": [
              {
                "o": {"x": 0.333, "y": 0},
                "i": {"x": 0.667, "y": 1},
                "s": [0],
                "t": 0
              },
              {
                "o": {"x": 0.167, "y": 0},
                "i": {"x": 0.667, "y": 1},
                "s": [360],
                "t": 32
              },
              {
                "o": {"x": 0.333, "y": 0},
                "i": {"x": 0.667, "y": 1},
                "s": [360],
                "t": 67
              },
              {"s": [0], "t": 99}
            ],
            "ix": 3
          },
          "s": {
            "a": 1,
            "k": [
              {
                "o": {"x": 0.65, "y": 0},
                "i": {"x": 0.624, "y": 0.572},
                "s": [0],
                "t": 0
              },
              {
                "o": {"x": 0.167, "y": 0.688},
                "i": {"x": 0.637, "y": 1},
                "s": [68.507],
                "t": 12
              },
              {
                "o": {"x": 0.167, "y": 0},
                "i": {"x": 0.833, "y": 1},
                "s": [100],
                "t": 32
              },
              {
                "o": {"x": 0.575, "y": 0},
                "i": {"x": 0.381, "y": 1},
                "s": [100],
                "t": 67
              },
              {"s": [0], "t": 99}
            ],
            "ix": 1
          },
          "m": 1
        }
      ],
      "ind": 1
    },
    {
      "ty": 4,
      "nm": "icon 5",
      "sr": 1,
      "st": 0,
      "op": 100,
      "ip": 0,
      "hd": false,
      "ddd": 0,
      "bm": 0,
      "hasMask": false,
      "ao": 0,
      "ks": {
        "a": {"a": 0, "k": [994, 438, 0], "ix": 1},
        "s": {"a": 0, "k": [400, 400, 100], "ix": 6},
        "sk": {"a": 0, "k": 0},
        "p": {"a": 0, "k": [100, 100, 0], "ix": 2},
        "r": {"a": 0, "k": 0, "ix": 10},
        "sa": {"a": 0, "k": 0},
        "o": {"a": 0, "k": 100, "ix": 11}
      },
      "ef": [],
      "shapes": [
        {
          "ty": "gr",
          "bm": 0,
          "hd": false,
          "mn": "ADBE Vector Group",
          "nm": "Group 1",
          "ix": 1,
          "cix": 2,
          "np": 2,
          "it": [
            {
              "ty": "sh",
              "bm": 0,
              "hd": false,
              "mn": "ADBE Vector Shape - Group",
              "nm": "Path 1",
              "ix": 1,
              "d": 1,
              "ks": {
                "a": 0,
                "k": {
                  "c": false,
                  "i": [
                    [0, 0],
                    [1.223, -1.958],
                    [9.112, 5.944],
                    [-2.064, 3.303],
                    [-9.112, -5.944],
                    [-1.979, -1.867]
                  ],
                  "o": [
                    [3.33, 3.708],
                    [-2.064, 3.303],
                    [-9.112, -5.944],
                    [2.064, -3.303],
                    [2.675, 1.745],
                    [0, 0]
                  ],
                  "v": [
                    [12.882, 1.664],
                    [16.498, 10.762],
                    [-3.737, 5.981],
                    [-16.498, -10.762],
                    [3.737, -5.981],
                    [10.773, -0.49]
                  ]
                },
                "ix": 2
              }
            },
            {
              "ty": "st",
              "bm": 0,
              "hd": false,
              "mn": "ADBE Vector Graphic - Stroke",
              "nm": "Stroke 1",
              "lc": 2,
              "lj": 2,
              "ml": 1,
              "o": {"a": 0, "k": 100, "ix": 4},
              "w": {"a": 0, "k": 1.5, "ix": 5},
              "c": {"a": 0, "k": [0.702, 0.2431, 0.9843], "ix": 3}
            },
            {
              "ty": "tr",
              "a": {"a": 0, "k": [0, 0], "ix": 1},
              "s": {"a": 0, "k": [100, 100], "ix": 3},
              "sk": {"a": 0, "k": 0, "ix": 4},
              "p": {"a": 0, "k": [994, 438.147], "ix": 2},
              "r": {"a": 0, "k": 0, "ix": 6},
              "sa": {"a": 0, "k": 0, "ix": 5},
              "o": {"a": 0, "k": 100, "ix": 7}
            }
          ]
        },
        {
          "ty": "gr",
          "bm": 0,
          "hd": false,
          "mn": "ADBE Vector Group",
          "nm": "Group 2",
          "ix": 2,
          "cix": 2,
          "np": 2,
          "it": [
            {
              "ty": "sh",
              "bm": 0,
              "hd": false,
              "mn": "ADBE Vector Shape - Group",
              "nm": "Path 1",
              "ix": 1,
              "d": 1,
              "ks": {
                "a": 0,
                "k": {
                  "c": false,
                  "i": [
                    [0, 0],
                    [1.738, 2.332],
                    [-9.097, 7.08],
                    [-2.313, -3.103],
                    [9.097, -7.08],
                    [1.231, -0.817]
                  ],
                  "o": [
                    [-6.564, 3.765],
                    [-2.313, -3.103],
                    [9.097, -7.08],
                    [2.313, 3.103],
                    [-1.243, 0.968],
                    [0, 0]
                  ],
                  "v": [
                    [-2.514, 10.145],
                    [-16.472, 12.819],
                    [-4.189, -5.619],
                    [16.472, -12.819],
                    [4.189, 5.619],
                    [0.469, 8.299]
                  ]
                },
                "ix": 2
              }
            },
            {
              "ty": "st",
              "bm": 0,
              "hd": false,
              "mn": "ADBE Vector Graphic - Stroke",
              "nm": "Stroke 1",
              "lc": 2,
              "lj": 2,
              "ml": 1,
              "o": {"a": 0, "k": 100, "ix": 4},
              "w": {"a": 0, "k": 1.5, "ix": 5},
              "c": {"a": 0, "k": [0.702, 0.2431, 0.9843], "ix": 3}
            },
            {
              "ty": "tr",
              "a": {"a": 0, "k": [0, 0], "ix": 1},
              "s": {"a": 0, "k": [100, 100], "ix": 3},
              "sk": {"a": 0, "k": 0, "ix": 4},
              "p": {"a": 0, "k": [994, 438.092], "ix": 2},
              "r": {"a": 0, "k": 0, "ix": 6},
              "sa": {"a": 0, "k": 0, "ix": 5},
              "o": {"a": 0, "k": 100, "ix": 7}
            }
          ]
        },
        {
          "ty": "gr",
          "bm": 0,
          "hd": false,
          "mn": "ADBE Vector Group",
          "nm": "Group 3",
          "ix": 3,
          "cix": 2,
          "np": 2,
          "it": [
            {
              "ty": "sh",
              "bm": 0,
              "hd": false,
              "mn": "ADBE Vector Shape - Group",
              "nm": "Path 1",
              "ix": 1,
              "d": 1,
              "ks": {
                "a": 0,
                "k": {
                  "c": false,
                  "i": [
                    [0, 0],
                    [-2.033, 0],
                    [0, -10.493],
                    [3.829, 0],
                    [0, 10.493],
                    [-0.755, 3.042]
                  ],
                  "o": [
                    [1.268, -3.819],
                    [3.829, 0],
                    [0, 10.493],
                    [-3.829, 0],
                    [0, -3.956],
                    [0, 0]
                  ],
                  "v": [
                    [-5.129, -12.783],
                    [0, -19],
                    [6.933, 0],
                    [0, 19],
                    [-6.933, 0],
                    [-5.737, -10.67]
                  ]
                },
                "ix": 2
              }
            },
            {
              "ty": "st",
              "bm": 0,
              "hd": false,
              "mn": "ADBE Vector Graphic - Stroke",
              "nm": "Stroke 1",
              "lc": 2,
              "lj": 2,
              "ml": 1,
              "o": {"a": 0, "k": 100, "ix": 4},
              "w": {"a": 0, "k": 1.5, "ix": 5},
              "c": {"a": 0, "k": [0.702, 0.2431, 0.9843], "ix": 3}
            },
            {
              "ty": "tr",
              "a": {"a": 0, "k": [0, 0], "ix": 1},
              "s": {"a": 0, "k": [100, 100], "ix": 3},
              "sk": {"a": 0, "k": 0, "ix": 4},
              "p": {"a": 0, "k": [993.999, 438], "ix": 2},
              "r": {"a": 0, "k": 0, "ix": 6},
              "sa": {"a": 0, "k": 0, "ix": 5},
              "o": {"a": 0, "k": 100, "ix": 7}
            }
          ]
        },
        {
          "ty": "gr",
          "bm": 0,
          "hd": false,
          "mn": "ADBE Vector Group",
          "nm": "Group 4",
          "ix": 4,
          "cix": 2,
          "np": 2,
          "it": [
            {
              "ty": "sh",
              "bm": 0,
              "hd": false,
              "mn": "ADBE Vector Shape - Group",
              "nm": "Path 1",
              "ix": 1,
              "d": 1,
              "ks": {
                "a": 0,
                "k": {
                  "c": true,
                  "i": [
                    [0, -1.105],
                    [1.105, 0],
                    [0, 1.105],
                    [-1.105, 0]
                  ],
                  "o": [
                    [0, 1.105],
                    [-1.105, 0],
                    [0, -1.105],
                    [1.105, 0]
                  ],
                  "v": [
                    [2, 0],
                    [0, 2],
                    [-2, 0],
                    [0, -2]
                  ]
                },
                "ix": 2
              }
            },
            {
              "ty": "st",
              "bm": 0,
              "hd": false,
              "mn": "ADBE Vector Graphic - Stroke",
              "nm": "Stroke 1",
              "lc": 2,
              "lj": 2,
              "ml": 1,
              "o": {"a": 0, "k": 100, "ix": 4},
              "w": {"a": 0, "k": 1.5, "ix": 5},
              "c": {"a": 0, "k": [0.0314, 0.9647, 0.5216], "ix": 3}
            },
            {
              "ty": "tr",
              "a": {"a": 0, "k": [0, 0], "ix": 1},
              "s": {"a": 0, "k": [100, 100], "ix": 3},
              "sk": {"a": 0, "k": 0, "ix": 4},
              "p": {"a": 0, "k": [993.999, 438], "ix": 2},
              "r": {"a": 0, "k": 0, "ix": 6},
              "sa": {"a": 0, "k": 0, "ix": 5},
              "o": {"a": 0, "k": 100, "ix": 7}
            }
          ]
        },
        {
          "ty": "tm",
          "bm": 0,
          "hd": false,
          "mn": "ADBE Vector Filter - Trim",
          "nm": "Trim Paths 1",
          "ix": 5,
          "e": {
            "a": 1,
            "k": [
              {
                "o": {"x": 0.167, "y": 0},
                "i": {"x": 0.833, "y": 1},
                "s": [50],
                "t": 0
              },
              {
                "o": {"x": 0.445, "y": 0},
                "i": {"x": 0.151, "y": 1},
                "s": [50],
                "t": 15
              },
              {
                "o": {"x": 0.163, "y": 0},
                "i": {"x": 0.785, "y": 1},
                "s": [0],
                "t": 35
              },
              {
                "o": {"x": 0.379, "y": 0},
                "i": {"x": 0.714, "y": 1},
                "s": [0],
                "t": 63
              },
              {
                "o": {"x": 0.849, "y": 0},
                "i": {"x": 0.555, "y": 1},
                "s": [100],
                "t": 64
              },
              {
                "o": {"x": 0.167, "y": 0},
                "i": {"x": 0.833, "y": 1},
                "s": [50],
                "t": 84
              },
              {"s": [50], "t": 99}
            ],
            "ix": 2
          },
          "o": {"a": 0, "k": 0, "ix": 3},
          "s": {
            "a": 1,
            "k": [
              {
                "o": {"x": 0.167, "y": 0},
                "i": {"x": 0.833, "y": 1},
                "s": [50],
                "t": 0
              },
              {
                "o": {"x": 0.445, "y": 0},
                "i": {"x": 0.151, "y": 1},
                "s": [50],
                "t": 15
              },
              {
                "o": {"x": 0.163, "y": 0},
                "i": {"x": 0.785, "y": 1},
                "s": [100],
                "t": 35
              },
              {
                "o": {"x": 0.379, "y": 0},
                "i": {"x": 0.714, "y": 1},
                "s": [100],
                "t": 63
              },
              {
                "o": {"x": 0.849, "y": 0},
                "i": {"x": 0.555, "y": 1},
                "s": [0],
                "t": 64
              },
              {
                "o": {"x": 0.167, "y": 0},
                "i": {"x": 0.833, "y": 1},
                "s": [50],
                "t": 84
              },
              {"s": [50], "t": 99}
            ],
            "ix": 1
          },
          "m": 1
        }
      ],
      "ind": 2
    }
  ],
  "v": "5.7.6",
  "fr": 20,
  "op": 100,
  "ip": 0,
  "assets": []
}
